LICENSE.txt
MANIFEST.in
README.rst
setup.cfg
setup.py
docs/HISTORY.rst
fez/__init__.py
fez.djangoskel.egg-info/PKG-INFO
fez.djangoskel.egg-info/SOURCES.txt
fez.djangoskel.egg-info/dependency_links.txt
fez.djangoskel.egg-info/entry_points.txt
fez.djangoskel.egg-info/namespace_packages.txt
fez.djangoskel.egg-info/not-zip-safe
fez.djangoskel.egg-info/requires.txt
fez.djangoskel.egg-info/top_level.txt
fez/djangoskel/__init__.py
fez/djangoskel/pastertemplates.py
fez/djangoskel/templates/django_app/README.txt_tmpl
fez/djangoskel/templates/django_app/setup.cfg
fez/djangoskel/templates/django_app/setup.py_tmpl
fez/djangoskel/templates/django_app/+project+/__init__.py
fez/djangoskel/templates/django_app/+project+/admin.py_tmpl
fez/djangoskel/templates/django_app/+project+/models.py
fez/djangoskel/templates/django_app/+project+/test_settings.py_tmpl
fez/djangoskel/templates/django_app/+project+/test_urls.py_tmpl
fez/djangoskel/templates/django_app/+project+/tests.py_tmpl
fez/djangoskel/templates/django_app/+project+/urls.py_tmpl
fez/djangoskel/templates/django_app/+project+/views.py
fez/djangoskel/templates/django_app/docs/HISTORY.txt_tmpl
fez/djangoskel/templates/django_buildout/README.txt
fez/djangoskel/templates/django_buildout/bootstrap.py
fez/djangoskel/templates/django_buildout/buildout.cfg_tmpl
fez/djangoskel/templates/django_buildout/devel.cfg_tmpl
fez/djangoskel/templates/django_namespace_app/README.txt_tmpl
fez/djangoskel/templates/django_namespace_app/setup.cfg
fez/djangoskel/templates/django_namespace_app/setup.py_tmpl
fez/djangoskel/templates/django_namespace_app/+namespace_package+/__init__.py
fez/djangoskel/templates/django_namespace_app/+namespace_package+/+package+/__init__.py
fez/djangoskel/templates/django_namespace_app/+namespace_package+/+package+/admin.py_tmpl
fez/djangoskel/templates/django_namespace_app/+namespace_package+/+package+/models.py
fez/djangoskel/templates/django_namespace_app/+namespace_package+/+package+/test_settings.py_tmpl
fez/djangoskel/templates/django_namespace_app/+namespace_package+/+package+/test_urls.py_tmpl
fez/djangoskel/templates/django_namespace_app/+namespace_package+/+package+/tests.py_tmpl
fez/djangoskel/templates/django_namespace_app/+namespace_package+/+package+/urls.py_tmpl
