Metadata-Version: 1.0
Name: fez.djangoskel
Version: 0.3.0
Summary: Paster templates for creating Django applications as eggs
Home-page: http://www.fezconsulting.com
Author: Dan Fairs
Author-email: dan@fezconsulting.com
License: BSD
Platform: UNKNOWN
Classifier: Programming Language :: Python
Classifier: Topic :: Software Development :: Libraries :: Python Modules
Classifier: Development Status :: 4 - Beta
Classifier: Environment :: Plugins
Classifier: Framework :: Paste
Classifier: Intended Audience :: Developers
Classifier: License :: OSI Approved :: BSD License
Classifier: Framework :: Django
